autodistill_grounded_sam_2/__init__.py
autodistill_grounded_sam_2/grounded_sam_2.py
autodistill_grounded_sam_2/helpers.py
autodistill_grounded_sam_2-0.1.0.dist-info/LICENSE
autodistill_grounded_sam_2-0.1.0.dist-info/METADATA
autodistill_grounded_sam_2-0.1.0.dist-info/WHEEL
autodistill_grounded_sam_2-0.1.0.dist-info/top_level.txt
autodistill_grounded_sam_2-0.1.0.dist-info/RECORD
